[
  {
    "eventName": "TossConf'25",
    "eventDescription": "TOSSConf25 (Tamil Open Source Software Conference 2025) is a community-driven event celebrating open-source software and Tamil computing. Scheduled for July 18–19, 2025, at St. Joseph’s Institute of Technology in Semmancheri, Chennai, the conference aims to bring together developers, contributors, and enthusiasts to promote open source initiatives in Tamil Nadu.",
    "eventDate": "2025-07-18",
    "eventTime": "09:30",
    "eventVenue": "St. Joseph's Institute of Technology, Old Mahabalipuram Road, Kamaraj Nagar, Semmancheri, Chennai, Tamil Nadu 600119 ",
    "eventLink": "https://tossconf25.kaniyam.com/",
    "location": "Chennai",
    "communityName": "TossConf25",
    "communityLogo": "https://i.ibb.co/fWZCQww/hero-bg1.png"
  },
  {
    "eventName": "The Future is Now: SRE Powered by AI & Hyper-Automated Healing",
    "eventDescription": "AI is now the norm, and Hyper Automation enables fully self-healing, zero-touch systems",
    "eventDate": "2025-07-05",
    "eventTime": "10:30",
    "eventVenue": "New cafe,3rd floor ,Audi - 2,HCL Technologies, Gate 1, Elcot SEZ, Sholinganallur, Chennai 600119",
    "eventLink": "https://www.meetup.com/chennai-site-reliability-engineering-meetup-group/events/308535503/?eventOrigin=group_upcoming_events",
    "location": "Chennai",
    "communityName": "Chennai Site Reliability Engineering",
    "communityLogo": "https://i.ibb.co/xt5zTSMG/SRElogo.jpg"
  }
]
